regentic/__init__.py
tests/__init__.py
regentic-0.0.1a0.dist-info/METADATA
regentic-0.0.1a0.dist-info/WHEEL
regentic-0.0.1a0.dist-info/top_level.txt
regentic-0.0.1a0.dist-info/RECORD
