Metadata-Version: 2.1
Name: regentic
Version: 0.0.1a0
Home-page: https://github.com/greysonlalonde/regentic
Download-URL: https://github.com/greysonlalonde/regentic/v0.0.1-alpha.tar.gz
Author: Greyson R. LaLonde
Author-email: "Greyson R. LaLonde" <greyson.r.lalonde@gmail.com>
Project-URL: homepage, https://github.com/greysonlalonde/regentic
Project-URL: documentation, https://github.com/greysonlalonde/regentic
Project-URL: tracker, https://github.com/greysonlalonde/regentic/issues
Classifier: License :: OSI Approved :: MIT License
Classifier: Development Status :: 2 - Pre-Alpha
Classifier: Programming Language :: Python
Classifier: Programming Language :: Python :: 3
Classifier: Topic :: Software Development :: Libraries :: Python Modules
Classifier: Intended Audience :: Developers
Classifier: Operating System :: Microsoft :: Windows
Classifier: Operating System :: POSIX :: Linux
Classifier: Operating System :: POSIX
Classifier: Operating System :: Unix
Classifier: Operating System :: MacOS
Requires-Python: >=3.10
Provides-Extra: dev
Requires-Dist: mypy==1.14.0; extra == "dev"
Requires-Dist: black==24.10.0; extra == "dev"
Requires-Dist: pylint==3.3.3; extra == "dev"
Requires-Dist: isort==5.13.2; extra == "dev"
Requires-Dist: flake8==7.1.1; extra == "dev"
Requires-Dist: autoflake==2.3.1; extra == "dev"
Provides-Extra: doc
